{"textures":{"0":"modelengine:entity/magononea","1":"modelengine:entity/capanorrea","2":"modelengine:entity/3"},"elements":[{"name":"3_0","from":[11.57031,7.483971,-4.923975],"to":[13.9428005,7.9584694,-3.0259833],"rotation":{"angle":0.0,"axis":"x","origin":[8.115861,7.7212195,7.534046]},"faces":{"down":{"uv":[6.5,1.5,7.75,0.5],"rotation":0,"texture":"#2","tintindex":0},"east":{"uv":[7.5,0.5,7.75,1.5],"rotation":90,"texture":"#2","tintindex":0},"north":{"uv":[7.75,0.5,6.5,0.75],"rotation":0,"texture":"#2","tintindex":0},"south":{"uv":[6.5,1.25,7.75,1.5],"rotation":0,"texture":"#2","tintindex":0},"up":{"uv":[6.5,0.5,7.75,1.5],"rotation":0,"texture":"#2","tintindex":0},"west":{"uv":[6.5,0.5,6.75,1.5],"rotation":270,"texture":"#2","tintindex":0}}},{"name":"3_1","from":[13.9428005,7.483971,-4.923975],"to":[14.891796,7.9584694,-3.5004807],"rotation":{"angle":0.0,"axis":"x","origin":[8.115861,7.7212195,7.534046]},"faces":{"down":{"uv":[7.75,1.25,8.25,0.5],"rotation":0,"texture":"#2","tintindex":0},"east":{"uv":[8.0,0.5,8.25,1.25],"rotation":90,"texture":"#2","tintindex":0},"north":{"uv":[8.25,0.5,7.75,0.75],"rotation":0,"texture":"#2","tintindex":0},"south":{"uv":[7.75,1.0,8.25,1.25],"rotation":0,"texture":"#2","tintindex":0},"up":{"uv":[7.75,0.5,8.25,1.25],"rotation":0,"texture":"#2","tintindex":0},"west":{"uv":[7.75,0.5,8.0,1.25],"rotation":270,"texture":"#2","tintindex":0}}},{"name":"3_2","from":[14.891796,7.483971,-4.923975],"to":[15.840792,7.9584694,-4.4494777],"rotation":{"angle":0.0,"axis":"x","origin":[8.115861,7.7212195,7.534046]},"faces":{"down":{"uv":[8.25,0.75,8.75,0.5],"rotation":0,"texture":"#2","tintindex":0},"east":{"uv":[8.5,0.5,8.75,0.75],"rotation":90,"texture":"#2","tintindex":0},"north":{"uv":[8.75,0.5,8.25,0.75],"rotation":0,"texture":"#2","tintindex":0},"south":{"uv":[8.25,0.5,8.75,0.75],"rotation":0,"texture":"#2","tintindex":0},"up":{"uv":[8.25,0.5,8.75,0.75],"rotation":0,"texture":"#2","tintindex":0},"west":{"uv":[8.25,0.5,8.5,0.75],"rotation":270,"texture":"#2","tintindex":0}}},{"name":"3_3","from":[11.095812,7.483971,-4.4494777],"to":[11.57031,7.9584694,2.6679938],"rotation":{"angle":0.0,"axis":"x","origin":[8.115861,7.7212195,7.534046]},"faces":{"down":{"uv":[6.25,4.5,6.5,0.75],"rotation":0,"texture":"#2","tintindex":0},"east":{"uv":[6.25,0.75,6.5,4.5],"rotation":90,"texture":"#2","tintindex":0},"north":{"uv":[6.5,0.75,6.25,1.0],"rotation":0,"texture":"#2","tintindex":0},"south":{"uv":[6.25,4.25,6.5,4.5],"rotation":0,"texture":"#2","tintindex":0},"up":{"uv":[6.25,0.75,6.5,4.5],"rotation":0,"texture":"#2","tintindex":0},"west":{"uv":[6.25,0.75,6.5,4.5],"rotation":270,"texture":"#2","tintindex":0}}},{"name":"3_4","from":[15.366295,7.483971,-4.4494777],"to":[16.789787,7.9584694,-3.974979],"rotation":{"angle":0.0,"axis":"x","origin":[8.115861,7.7212195,7.534046]},"faces":{"down":{"uv":[8.5,1.0,9.25,0.75],"rotation":0,"texture":"#2","tintindex":0},"east":{"uv":[9.0,0.75,9.25,1.0],"rotation":90,"texture":"#2","tintindex":0},"north":{"uv":[9.25,0.75,8.5,1.0],"rotation":0,"texture":"#2","tintindex":0},"south":{"uv":[8.5,0.75,9.25,1.0],"rotation":0,"texture":"#2","tintindex":0},"up":{"uv":[8.5,0.75,9.25,1.0],"rotation":0,"texture":"#2","tintindex":0},"west":{"uv":[8.5,0.75,8.75,1.0],"rotation":270,"texture":"#2","tintindex":0}}},{"name":"3_5","from":[10.621314,7.483971,-3.974979],"to":[11.095812,7.9584694,3.1424909],"rotation":{"angle":0.0,"axis":"x","origin":[8.115861,7.7212195,7.534046]},"faces":{"down":{"uv":[6.0,4.75,6.25,1.0],"rotation":0,"texture":"#2","tintindex":0},"east":{"uv":[6.0,1.0,6.25,4.75],"rotation":90,"texture":"#2","tintindex":0},"north":{"uv":[6.25,1.0,6.0,1.25],"rotation":0,"texture":"#2","tintindex":0},"south":{"uv":[6.0,4.5,6.25,4.75],"rotation":0,"texture":"#2","tintindex":0},"up":{"uv":[6.0,1.0,6.25,4.75],"rotation":0,"texture":"#2","tintindex":0},"west":{"uv":[6.0,1.0,6.25,4.75],"rotation":270,"texture":"#2","tintindex":0}}},{"name":"3_6","from":[14.891796,7.483971,-3.974979],"to":[15.366295,7.9584694,-3.5004807],"rotation":{"angle":0.0,"axis":"x","origin":[8.115861,7.7212195,7.534046]},"faces":{"down":{"uv":[8.25,1.25,8.5,1.0],"rotation":0,"texture":"#2","tintindex":0},"east":{"uv":[8.25,1.0,8.5,1.25],"rotation":90,"texture":"#2","tintindex":0},"north":{"uv":[8.5,1.0,8.25,1.25],"rotation":0,"texture":"#2","tintindex":0},"south":{"uv":[8.25,1.0,8.5,1.25],"rotation":0,"texture":"#2","tintindex":0},"up":{"uv":[8.25,1.0,8.5,1.25],"rotation":0,"texture":"#2","tintindex":0},"west":{"uv":[8.25,1.0,8.5,1.25],"rotation":270,"texture":"#2","tintindex":0}}},{"name":"3_7","from":[10.146816,7.483971,-3.0259833],"to":[10.621314,7.9584694,3.6169891],"rotation":{"angle":0.0,"axis":"x","origin":[8.115861,7.7212195,7.534046]},"faces":{"down":{"uv":[5.75,5.0,6.0,1.5],"rotation":0,"texture":"#2","tintindex":0},"east":{"uv":[5.75,1.5,6.0,5.0],"rotation":90,"texture":"#2","tintindex":0},"north":{"uv":[6.0,1.5,5.75,1.75],"rotation":0,"texture":"#2","tintindex":0},"south":{"uv":[5.75,4.75,6.0,5.0],"rotation":0,"texture":"#2","tintindex":0},"up":{"uv":[5.75,1.5,6.0,5.0],"rotation":0,"texture":"#2","tintindex":0},"west":{"uv":[5.75,1.5,6.0,5.0],"rotation":270,"texture":"#2","tintindex":0}}},{"name":"3_8","from":[11.57031,7.483971,-3.0259833],"to":[12.519306,7.9584694,-1.6024895],"rotation":{"angle":0.0,"axis":"x","origin":[8.115861,7.7212195,7.534046]},"faces":{"down":{"uv":[6.5,2.25,7.0,1.5],"rotation":0,"texture":"#2","tintindex":0},"east":{"uv":[6.75,1.5,7.0,2.25],"rotation":90,"texture":"#2","tintindex":0},"north":{"uv":[7.0,1.5,6.5,1.75],"rotation":0,"texture":"#2","tintindex":0},"south":{"uv":[6.5,2.0,7.0,2.25],"rotation":0,"texture":"#2","tintindex":0},"up":{"uv":[6.5,1.5,7.0,2.25],"rotation":0,"texture":"#2","tintindex":0},"west":{"uv":[6.5,1.5,6.75,2.25],"rotation":270,"texture":"#2","tintindex":0}}},{"name":"3_9","from":[12.519306,7.483971,-3.0259833],"to":[12.993804,7.9584694,-2.551485],"rotation":{"angle":0.0,"axis":"x","origin":[8.115861,7.7212195,7.534046]},"faces":{"down":{"uv":[7.0,1.75,7.25,1.5],"rotation":0,"texture":"#2","tintindex":0},"east":{"uv":[7.0,1.5,7.25,1.75],"rotation":90,"texture":"#2","tintindex":0},"north":{"uv":[7.25,1.5,7.0,1.75],"rotation":0,"texture":"#2","tintindex":0},"south":{"uv":[7.0,1.5,7.25,1.75],"rotation":0,"texture":"#2","tintindex":0},"up":{"uv":[7.0,1.5,7.25,1.75],"rotation":0,"texture":"#2","tintindex":0},"west":{"uv":[7.0,1.5,7.25,1.75],"rotation":270,"texture":"#2","tintindex":0}}},{"name":"3_13","from":[9.6723175,7.483971,-2.0769868],"to":[10.146816,7.9584694,1.2444986],"rotation":{"angle":0.0,"axis":"x","origin":[8.115861,7.7212195,7.534046]},"faces":{"down":{"uv":[5.5,3.75,5.75,2.0],"rotation":0,"texture":"#2","tintindex":0},"east":{"uv":[5.5,2.0,5.75,3.75],"rotation":90,"texture":"#2","tintindex":0},"north":{"uv":[5.75,2.0,5.5,2.25],"rotation":0,"texture":"#2","tintindex":0},"south":{"uv":[5.5,3.5,5.75,3.75],"rotation":0,"texture":"#2","tintindex":0},"up":{"uv":[5.5,2.0,5.75,3.75],"rotation":0,"texture":"#2","tintindex":0},"west":{"uv":[5.5,2.0,5.75,3.75],"rotation":270,"texture":"#2","tintindex":0}}},{"name":"3_16","from":[11.57031,7.483971,-1.6024895],"to":[12.044808,7.9584694,2.6679938],"rotation":{"angle":0.0,"axis":"x","origin":[8.115861,7.7212195,7.534046]},"faces":{"down":{"uv":[6.5,4.5,6.75,2.25],"rotation":0,"texture":"#2","tintindex":0},"east":{"uv":[6.5,2.25,6.75,4.5],"rotation":90,"texture":"#2","tintindex":0},"north":{"uv":[6.75,2.25,6.5,2.5],"rotation":0,"texture":"#2","tintindex":0},"south":{"uv":[6.5,4.25,6.75,4.5],"rotation":0,"texture":"#2","tintindex":0},"up":{"uv":[6.5,2.25,6.75,4.5],"rotation":0,"texture":"#2","tintindex":0},"west":{"uv":[6.5,2.25,6.75,4.5],"rotation":270,"texture":"#2","tintindex":0}}},{"name":"3_17","from":[20.111275,7.483971,-0.6534927],"to":[20.585773,7.9584694,5.040483],"rotation":{"angle":0.0,"axis":"x","origin":[8.115861,7.7212195,7.534046]},"faces":{"down":{"uv":[11.0,5.75,11.25,2.75],"rotation":0,"texture":"#2","tintindex":0},"east":{"uv":[11.0,2.75,11.25,5.75],"rotation":90,"texture":"#2","tintindex":0},"north":{"uv":[11.25,2.75,11.0,3.0],"rotation":0,"texture":"#2","tintindex":0},"south":{"uv":[11.0,5.5,11.25,5.75],"rotation":0,"texture":"#2","tintindex":0},"up":{"uv":[11.0,2.75,11.25,5.75],"rotation":0,"texture":"#2","tintindex":0},"west":{"uv":[11.0,2.75,11.25,5.75],"rotation":270,"texture":"#2","tintindex":0}}},{"name":"3_18","from":[12.044808,7.483971,-0.17899537],"to":[12.519306,7.9584694,0.7700014],"rotation":{"angle":0.0,"axis":"x","origin":[8.115861,7.7212195,7.534046]},"faces":{"down":{"uv":[6.75,3.5,7.0,3.0],"rotation":0,"texture":"#2","tintindex":0},"east":{"uv":[6.75,3.0,7.0,3.5],"rotation":90,"texture":"#2","tintindex":0},"north":{"uv":[7.0,3.0,6.75,3.25],"rotation":0,"texture":"#2","tintindex":0},"south":{"uv":[6.75,3.25,7.0,3.5],"rotation":0,"texture":"#2","tintindex":0},"up":{"uv":[6.75,3.0,7.0,3.5],"rotation":0,"texture":"#2","tintindex":0},"west":{"uv":[6.75,3.0,7.0,3.5],"rotation":270,"texture":"#2","tintindex":0}}},{"name":"3_19","from":[12.519306,7.483971,0.2955029],"to":[14.891796,7.9584694,4.091487],"rotation":{"angle":0.0,"axis":"x","origin":[8.115861,7.7212195,7.534046]},"faces":{"down":{"uv":[7.0,5.25,8.25,3.25],"rotation":0,"texture":"#2","tintindex":0},"east":{"uv":[8.0,3.25,8.25,5.25],"rotation":90,"texture":"#2","tintindex":0},"north":{"uv":[8.25,3.25,7.0,3.5],"rotation":0,"texture":"#2","tintindex":0},"south":{"uv":[7.0,5.0,8.25,5.25],"rotation":0,"texture":"#2","tintindex":0},"up":{"uv":[7.0,3.25,8.25,5.25],"rotation":0,"texture":"#2","tintindex":0},"west":{"uv":[7.0,3.25,7.25,5.25],"rotation":270,"texture":"#2","tintindex":0}}},{"name":"3_21","from":[20.585773,7.483971,0.2955029],"to":[21.060272,7.9584694,4.5659847],"rotation":{"angle":0.0,"axis":"x","origin":[8.115861,7.7212195,7.534046]},"faces":{"down":{"uv":[11.25,5.5,11.5,3.25],"rotation":0,"texture":"#2","tintindex":0},"east":{"uv":[11.25,3.25,11.5,5.5],"rotation":90,"texture":"#2","tintindex":0},"north":{"uv":[11.5,3.25,11.25,3.5],"rotation":0,"texture":"#2","tintindex":0},"south":{"uv":[11.25,5.25,11.5,5.5],"rotation":0,"texture":"#2","tintindex":0},"up":{"uv":[11.25,3.25,11.5,5.5],"rotation":0,"texture":"#2","tintindex":0},"west":{"uv":[11.25,3.25,11.5,5.5],"rotation":270,"texture":"#2","tintindex":0}}},{"name":"3_22","from":[14.891796,7.483971,0.7700014],"to":[15.366295,7.9584694,6.463977],"rotation":{"angle":0.0,"axis":"x","origin":[8.115861,7.7212195,7.534046]},"faces":{"down":{"uv":[8.25,6.5,8.5,3.5],"rotation":0,"texture":"#2","tintindex":0},"east":{"uv":[8.25,3.5,8.5,6.5],"rotation":90,"texture":"#2","tintindex":0},"north":{"uv":[8.5,3.5,8.25,3.75],"rotation":0,"texture":"#2","tintindex":0},"south":{"uv":[8.25,6.25,8.5,6.5],"rotation":0,"texture":"#2","tintindex":0},"up":{"uv":[8.25,3.5,8.5,6.5],"rotation":0,"texture":"#2","tintindex":0},"west":{"uv":[8.25,3.5,8.5,6.5],"rotation":270,"texture":"#2","tintindex":0}}},{"name":"3_23","from":[12.044808,7.483971,1.2444986],"to":[12.519306,7.9584694,5.040483],"rotation":{"angle":0.0,"axis":"x","origin":[8.115861,7.7212195,7.534046]},"faces":{"down":{"uv":[6.75,5.75,7.0,3.75],"rotation":0,"texture":"#2","tintindex":0},"east":{"uv":[6.75,3.75,7.0,5.75],"rotation":90,"texture":"#2","tintindex":0},"north":{"uv":[7.0,3.75,6.75,4.0],"rotation":0,"texture":"#2","tintindex":0},"south":{"uv":[6.75,5.5,7.0,5.75],"rotation":0,"texture":"#2","tintindex":0},"up":{"uv":[6.75,3.75,7.0,5.75],"rotation":0,"texture":"#2","tintindex":0},"west":{"uv":[6.75,3.75,7.0,5.75],"rotation":270,"texture":"#2","tintindex":0}}},{"name":"3_24","from":[15.366295,7.483971,1.2444986],"to":[15.840792,7.9584694,6.463977],"rotation":{"angle":0.0,"axis":"x","origin":[8.115861,7.7212195,7.534046]},"faces":{"down":{"uv":[8.5,6.5,8.75,3.75],"rotation":0,"texture":"#2","tintindex":0},"east":{"uv":[8.5,3.75,8.75,6.5],"rotation":90,"texture":"#2","tintindex":0},"north":{"uv":[8.75,3.75,8.5,4.0],"rotation":0,"texture":"#2","tintindex":0},"south":{"uv":[8.5,6.25,8.75,6.5],"rotation":0,"texture":"#2","tintindex":0},"up":{"uv":[8.5,3.75,8.75,6.5],"rotation":0,"texture":"#2","tintindex":0},"west":{"uv":[8.5,3.75,8.75,6.5],"rotation":270,"texture":"#2","tintindex":0}}},{"name":"3_25","from":[19.636776,7.483971,1.2444986],"to":[20.111275,7.9584694,5.514981],"rotation":{"angle":0.0,"axis":"x","origin":[8.115861,7.7212195,7.534046]},"faces":{"down":{"uv":[10.75,6.0,11.0,3.75],"rotation":0,"texture":"#2","tintindex":0},"east":{"uv":[10.75,3.75,11.0,6.0],"rotation":90,"texture":"#2","tintindex":0},"north":{"uv":[11.0,3.75,10.75,4.0],"rotation":0,"texture":"#2","tintindex":0},"south":{"uv":[10.75,5.75,11.0,6.0],"rotation":0,"texture":"#2","tintindex":0},"up":{"uv":[10.75,3.75,11.0,6.0],"rotation":0,"texture":"#2","tintindex":0},"west":{"uv":[10.75,3.75,11.0,6.0],"rotation":270,"texture":"#2","tintindex":0}}},{"name":"3_26","from":[9.6723175,7.483971,1.718997],"to":[10.146816,7.9584694,2.1934953],"rotation":{"angle":0.0,"axis":"x","origin":[8.115861,7.7212195,7.534046]},"faces":{"down":{"uv":[5.5,4.25,5.75,4.0],"rotation":0,"texture":"#2","tintindex":0},"east":{"uv":[5.5,4.0,5.75,4.25],"rotation":90,"texture":"#2","tintindex":0},"north":{"uv":[5.75,4.0,5.5,4.25],"rotation":0,"texture":"#2","tintindex":0},"south":{"uv":[5.5,4.0,5.75,4.25],"rotation":0,"texture":"#2","tintindex":0},"up":{"uv":[5.5,4.0,5.75,4.25],"rotation":0,"texture":"#2","tintindex":0},"west":{"uv":[5.5,4.0,5.75,4.25],"rotation":270,"texture":"#2","tintindex":0}}},{"name":"3_27","from":[19.162277,7.483971,2.1934953],"to":[19.636776,7.9584694,5.514981],"rotation":{"angle":0.0,"axis":"x","origin":[8.115861,7.7212195,7.534046]},"faces":{"down":{"uv":[10.5,6.0,10.75,4.25],"rotation":0,"texture":"#2","tintindex":0},"east":{"uv":[10.5,4.25,10.75,6.0],"rotation":90,"texture":"#2","tintindex":0},"north":{"uv":[10.75,4.25,10.5,4.5],"rotation":0,"texture":"#2","tintindex":0},"south":{"uv":[10.5,5.75,10.75,6.0],"rotation":0,"texture":"#2","tintindex":0},"up":{"uv":[10.5,4.25,10.75,6.0],"rotation":0,"texture":"#2","tintindex":0},"west":{"uv":[10.5,4.25,10.75,6.0],"rotation":270,"texture":"#2","tintindex":0}}},{"name":"3_28","from":[9.6723175,7.483971,3.1424909],"to":[10.146816,7.9584694,4.091487],"rotation":{"angle":0.0,"axis":"x","origin":[8.115861,7.7212195,7.534046]},"faces":{"down":{"uv":[5.5,5.25,5.75,4.75],"rotation":0,"texture":"#2","tintindex":0},"east":{"uv":[5.5,4.75,5.75,5.25],"rotation":90,"texture":"#2","tintindex":0},"north":{"uv":[5.75,4.75,5.5,5.0],"rotation":0,"texture":"#2","tintindex":0},"south":{"uv":[5.5,5.0,5.75,5.25],"rotation":0,"texture":"#2","tintindex":0},"up":{"uv":[5.5,4.75,5.75,5.25],"rotation":0,"texture":"#2","tintindex":0},"west":{"uv":[5.5,4.75,5.75,5.25],"rotation":270,"texture":"#2","tintindex":0}}},{"name":"3_29","from":[11.57031,7.483971,3.1424909],"to":[12.044808,7.9584694,5.514981],"rotation":{"angle":0.0,"axis":"x","origin":[8.115861,7.7212195,7.534046]},"faces":{"down":{"uv":[6.5,6.0,6.75,4.75],"rotation":0,"texture":"#2","tintindex":0},"east":{"uv":[6.5,4.75,6.75,6.0],"rotation":90,"texture":"#2","tintindex":0},"north":{"uv":[6.75,4.75,6.5,5.0],"rotation":0,"texture":"#2","tintindex":0},"south":{"uv":[6.5,5.75,6.75,6.0],"rotation":0,"texture":"#2","tintindex":0},"up":{"uv":[6.5,4.75,6.75,6.0],"rotation":0,"texture":"#2","tintindex":0},"west":{"uv":[6.5,4.75,6.75,6.0],"rotation":270,"texture":"#2","tintindex":0}}},{"name":"3_30","from":[18.687778,7.483971,3.1424909],"to":[19.162277,7.9584694,5.989479],"rotation":{"angle":0.0,"axis":"x","origin":[8.115861,7.7212195,7.534046]},"faces":{"down":{"uv":[10.25,6.25,10.5,4.75],"rotation":0,"texture":"#2","tintindex":0},"east":{"uv":[10.25,4.75,10.5,6.25],"rotation":90,"texture":"#2","tintindex":0},"north":{"uv":[10.5,4.75,10.25,5.0],"rotation":0,"texture":"#2","tintindex":0},"south":{"uv":[10.25,6.0,10.5,6.25],"rotation":0,"texture":"#2","tintindex":0},"up":{"uv":[10.25,4.75,10.5,6.25],"rotation":0,"texture":"#2","tintindex":0},"west":{"uv":[10.25,4.75,10.5,6.25],"rotation":270,"texture":"#2","tintindex":0}}},{"name":"3_31","from":[8.723322,7.483971,3.6169891],"to":[9.6723175,7.9584694,5.040483],"rotation":{"angle":0.0,"axis":"x","origin":[8.115861,7.7212195,7.534046]},"faces":{"down":{"uv":[5.0,5.75,5.5,5.0],"rotation":0,"texture":"#2","tintindex":0},"east":{"uv":[5.25,5.0,5.5,5.75],"rotation":90,"texture":"#2","tintindex":0},"north":{"uv":[5.5,5.0,5.0,5.25],"rotation":0,"texture":"#2","tintindex":0},"south":{"uv":[5.0,5.5,5.5,5.75],"rotation":0,"texture":"#2","tintindex":0},"up":{"uv":[5.0,5.0,5.5,5.75],"rotation":0,"texture":"#2","tintindex":0},"west":{"uv":[5.0,5.0,5.25,5.75],"rotation":270,"texture":"#2","tintindex":0}}},{"name":"3_32","from":[11.095812,7.483971,3.6169891],"to":[11.57031,7.9584694,5.989479],"rotation":{"angle":0.0,"axis":"x","origin":[8.115861,7.7212195,7.534046]},"faces":{"down":{"uv":[6.25,6.25,6.5,5.0],"rotation":0,"texture":"#2","tintindex":0},"east":{"uv":[6.25,5.0,6.5,6.25],"rotation":90,"texture":"#2","tintindex":0},"north":{"uv":[6.5,5.0,6.25,5.25],"rotation":0,"texture":"#2","tintindex":0},"south":{"uv":[6.25,6.0,6.5,6.25],"rotation":0,"texture":"#2","tintindex":0},"up":{"uv":[6.25,5.0,6.5,6.25],"rotation":0,"texture":"#2","tintindex":0},"west":{"uv":[6.25,5.0,6.5,6.25],"rotation":270,"texture":"#2","tintindex":0}}},{"name":"3_33","from":[15.840792,7.483971,3.6169891],"to":[16.31529,7.9584694,6.463977],"rotation":{"angle":0.0,"axis":"x","origin":[8.115861,7.7212195,7.534046]},"faces":{"down":{"uv":[8.75,6.5,9.0,5.0],"rotation":0,"texture":"#2","tintindex":0},"east":{"uv":[8.75,5.0,9.0,6.5],"rotation":90,"texture":"#2","tintindex":0},"north":{"uv":[9.0,5.0,8.75,5.25],"rotation":0,"texture":"#2","tintindex":0},"south":{"uv":[8.75,6.25,9.0,6.5],"rotation":0,"texture":"#2","tintindex":0},"up":{"uv":[8.75,5.0,9.0,6.5],"rotation":0,"texture":"#2","tintindex":0},"west":{"uv":[8.75,5.0,9.0,6.5],"rotation":270,"texture":"#2","tintindex":0}}},{"name":"3_34","from":[17.738785,7.483971,3.6169891],"to":[18.687778,7.9584694,5.989479],"rotation":{"angle":0.0,"axis":"x","origin":[8.115861,7.7212195,7.534046]},"faces":{"down":{"uv":[9.75,6.25,10.25,5.0],"rotation":0,"texture":"#2","tintindex":0},"east":{"uv":[10.0,5.0,10.25,6.25],"rotation":90,"texture":"#2","tintindex":0},"north":{"uv":[10.25,5.0,9.75,5.25],"rotation":0,"texture":"#2","tintindex":0},"south":{"uv":[9.75,6.0,10.25,6.25],"rotation":0,"texture":"#2","tintindex":0},"up":{"uv":[9.75,5.0,10.25,6.25],"rotation":0,"texture":"#2","tintindex":0},"west":{"uv":[9.75,5.0,10.0,6.25],"rotation":270,"texture":"#2","tintindex":0}}},{"name":"3_35","from":[10.621314,7.483971,4.091487],"to":[11.095812,7.9584694,5.989479],"rotation":{"angle":0.0,"axis":"x","origin":[8.115861,7.7212195,7.534046]},"faces":{"down":{"uv":[6.0,6.25,6.25,5.25],"rotation":0,"texture":"#2","tintindex":0},"east":{"uv":[6.0,5.25,6.25,6.25],"rotation":90,"texture":"#2","tintindex":0},"north":{"uv":[6.25,5.25,6.0,5.5],"rotation":0,"texture":"#2","tintindex":0},"south":{"uv":[6.0,6.0,6.25,6.25],"rotation":0,"texture":"#2","tintindex":0},"up":{"uv":[6.0,5.25,6.25,6.25],"rotation":0,"texture":"#2","tintindex":0},"west":{"uv":[6.0,5.25,6.25,6.25],"rotation":270,"texture":"#2","tintindex":0}}},{"name":"3_36","from":[12.519306,7.483971,4.091487],"to":[12.993804,7.9584694,4.5659847],"rotation":{"angle":0.0,"axis":"x","origin":[8.115861,7.7212195,7.534046]},"faces":{"down":{"uv":[7.0,5.5,7.25,5.25],"rotation":0,"texture":"#2","tintindex":0},"east":{"uv":[7.0,5.25,7.25,5.5],"rotation":90,"texture":"#2","tintindex":0},"north":{"uv":[7.25,5.25,7.0,5.5],"rotation":0,"texture":"#2","tintindex":0},"south":{"uv":[7.0,5.25,7.25,5.5],"rotation":0,"texture":"#2","tintindex":0},"up":{"uv":[7.0,5.25,7.25,5.5],"rotation":0,"texture":"#2","tintindex":0},"west":{"uv":[7.0,5.25,7.25,5.5],"rotation":270,"texture":"#2","tintindex":0}}},{"name":"3_37","from":[13.468302,7.483971,4.091487],"to":[14.891796,7.9584694,5.989479],"rotation":{"angle":0.0,"axis":"x","origin":[8.115861,7.7212195,7.534046]},"faces":{"down":{"uv":[7.5,6.25,8.25,5.25],"rotation":0,"texture":"#2","tintindex":0},"east":{"uv":[8.0,5.25,8.25,6.25],"rotation":90,"texture":"#2","tintindex":0},"north":{"uv":[8.25,5.25,7.5,5.5],"rotation":0,"texture":"#2","tintindex":0},"south":{"uv":[7.5,6.0,8.25,6.25],"rotation":0,"texture":"#2","tintindex":0},"up":{"uv":[7.5,5.25,8.25,6.25],"rotation":0,"texture":"#2","tintindex":0},"west":{"uv":[7.5,5.25,7.75,6.25],"rotation":270,"texture":"#2","tintindex":0}}},{"name":"3_38","from":[16.31529,7.483971,4.091487],"to":[17.738785,7.9584694,6.463977],"rotation":{"angle":0.0,"axis":"x","origin":[8.115861,7.7212195,7.534046]},"faces":{"down":{"uv":[9.0,6.5,9.75,5.25],"rotation":0,"texture":"#2","tintindex":0},"east":{"uv":[9.5,5.25,9.75,6.5],"rotation":90,"texture":"#2","tintindex":0},"north":{"uv":[9.75,5.25,9.0,5.5],"rotation":0,"texture":"#2","tintindex":0},"south":{"uv":[9.0,6.25,9.75,6.5],"rotation":0,"texture":"#2","tintindex":0},"up":{"uv":[9.0,5.25,9.75,6.5],"rotation":0,"texture":"#2","tintindex":0},"west":{"uv":[9.0,5.25,9.25,6.5],"rotation":270,"texture":"#2","tintindex":0}}},{"name":"3_39","from":[10.146816,7.483971,4.5659847],"to":[10.621314,7.9584694,6.463977],"rotation":{"angle":0.0,"axis":"x","origin":[8.115861,7.7212195,7.534046]},"faces":{"down":{"uv":[5.75,6.5,6.0,5.5],"rotation":0,"texture":"#2","tintindex":0},"east":{"uv":[5.75,5.5,6.0,6.5],"rotation":90,"texture":"#2","tintindex":0},"north":{"uv":[6.0,5.5,5.75,5.75],"rotation":0,"texture":"#2","tintindex":0},"south":{"uv":[5.75,6.25,6.0,6.5],"rotation":0,"texture":"#2","tintindex":0},"up":{"uv":[5.75,5.5,6.0,6.5],"rotation":0,"texture":"#2","tintindex":0},"west":{"uv":[5.75,5.5,6.0,6.5],"rotation":270,"texture":"#2","tintindex":0}}},{"name":"3_40","from":[8.248823,7.483971,5.040483],"to":[9.19782,7.9584694,5.989479],"rotation":{"angle":0.0,"axis":"x","origin":[8.115861,7.7212195,7.534046]},"faces":{"down":{"uv":[4.75,6.25,5.25,5.75],"rotation":0,"texture":"#2","tintindex":0},"east":{"uv":[5.0,5.75,5.25,6.25],"rotation":90,"texture":"#2","tintindex":0},"north":{"uv":[5.25,5.75,4.75,6.0],"rotation":0,"texture":"#2","tintindex":0},"south":{"uv":[4.75,6.0,5.25,6.25],"rotation":0,"texture":"#2","tintindex":0},"up":{"uv":[4.75,5.75,5.25,6.25],"rotation":0,"texture":"#2","tintindex":0},"west":{"uv":[4.75,5.75,5.0,6.25],"rotation":270,"texture":"#2","tintindex":0}}},{"name":"3_41","from":[12.993804,7.483971,5.040483],"to":[13.468302,7.9584694,5.989479],"rotation":{"angle":0.0,"axis":"x","origin":[8.115861,7.7212195,7.534046]},"faces":{"down":{"uv":[7.25,6.25,7.5,5.75],"rotation":0,"texture":"#2","tintindex":0},"east":{"uv":[7.25,5.75,7.5,6.25],"rotation":90,"texture":"#2","tintindex":0},"north":{"uv":[7.5,5.75,7.25,6.0],"rotation":0,"texture":"#2","tintindex":0},"south":{"uv":[7.25,6.0,7.5,6.25],"rotation":0,"texture":"#2","tintindex":0},"up":{"uv":[7.25,5.75,7.5,6.25],"rotation":0,"texture":"#2","tintindex":0},"west":{"uv":[7.25,5.75,7.5,6.25],"rotation":270,"texture":"#2","tintindex":0}}},{"name":"3_42","from":[9.6723175,7.483971,5.514981],"to":[10.146816,7.9584694,6.9384747],"rotation":{"angle":0.0,"axis":"x","origin":[8.115861,7.7212195,7.534046]},"faces":{"down":{"uv":[5.5,6.75,5.75,6.0],"rotation":0,"texture":"#2","tintindex":0},"east":{"uv":[5.5,6.0,5.75,6.75],"rotation":90,"texture":"#2","tintindex":0},"north":{"uv":[5.75,6.0,5.5,6.25],"rotation":0,"texture":"#2","tintindex":0},"south":{"uv":[5.5,6.5,5.75,6.75],"rotation":0,"texture":"#2","tintindex":0},"up":{"uv":[5.5,6.0,5.75,6.75],"rotation":0,"texture":"#2","tintindex":0},"west":{"uv":[5.5,6.0,5.75,6.75],"rotation":270,"texture":"#2","tintindex":0}}},{"name":"3_43","from":[12.519306,7.483971,5.514981],"to":[12.993804,7.9584694,6.463977],"rotation":{"angle":0.0,"axis":"x","origin":[8.115861,7.7212195,7.534046]},"faces":{"down":{"uv":[7.0,6.5,7.25,6.0],"rotation":0,"texture":"#2","tintindex":0},"east":{"uv":[7.0,6.0,7.25,6.5],"rotation":90,"texture":"#2","tintindex":0},"north":{"uv":[7.25,6.0,7.0,6.25],"rotation":0,"texture":"#2","tintindex":0},"south":{"uv":[7.0,6.25,7.25,6.5],"rotation":0,"texture":"#2","tintindex":0},"up":{"uv":[7.0,6.0,7.25,6.5],"rotation":0,"texture":"#2","tintindex":0},"west":{"uv":[7.0,6.0,7.25,6.5],"rotation":270,"texture":"#2","tintindex":0}}},{"name":"3_44","from":[8.248823,7.483971,5.989479],"to":[8.723322,7.9584694,6.463977],"rotation":{"angle":0.0,"axis":"x","origin":[8.115861,7.7212195,7.534046]},"faces":{"down":{"uv":[4.75,6.5,5.0,6.25],"rotation":0,"texture":"#2","tintindex":0},"east":{"uv":[4.75,6.25,5.0,6.5],"rotation":90,"texture":"#2","tintindex":0},"north":{"uv":[5.0,6.25,4.75,6.5],"rotation":0,"texture":"#2","tintindex":0},"south":{"uv":[4.75,6.25,5.0,6.5],"rotation":0,"texture":"#2","tintindex":0},"up":{"uv":[4.75,6.25,5.0,6.5],"rotation":0,"texture":"#2","tintindex":0},"west":{"uv":[4.75,6.25,5.0,6.5],"rotation":270,"texture":"#2","tintindex":0}}},{"name":"3_45","from":[9.19782,7.483971,5.989479],"to":[9.6723175,7.9584694,7.4129734],"rotation":{"angle":0.0,"axis":"x","origin":[8.115861,7.7212195,7.534046]},"faces":{"down":{"uv":[5.25,7.0,5.5,6.25],"rotation":0,"texture":"#2","tintindex":0},"east":{"uv":[5.25,6.25,5.5,7.0],"rotation":90,"texture":"#2","tintindex":0},"north":{"uv":[5.5,6.25,5.25,6.5],"rotation":0,"texture":"#2","tintindex":0},"south":{"uv":[5.25,6.75,5.5,7.0],"rotation":0,"texture":"#2","tintindex":0},"up":{"uv":[5.25,6.25,5.5,7.0],"rotation":0,"texture":"#2","tintindex":0},"west":{"uv":[5.25,6.25,5.5,7.0],"rotation":270,"texture":"#2","tintindex":0}}},{"name":"3_46","from":[12.044808,7.483971,5.989479],"to":[12.519306,7.9584694,7.4129734],"rotation":{"angle":0.0,"axis":"x","origin":[8.115861,7.7212195,7.534046]},"faces":{"down":{"uv":[6.75,7.0,7.0,6.25],"rotation":0,"texture":"#2","tintindex":0},"east":{"uv":[6.75,6.25,7.0,7.0],"rotation":90,"texture":"#2","tintindex":0},"north":{"uv":[7.0,6.25,6.75,6.5],"rotation":0,"texture":"#2","tintindex":0},"south":{"uv":[6.75,6.75,7.0,7.0],"rotation":0,"texture":"#2","tintindex":0},"up":{"uv":[6.75,6.25,7.0,7.0],"rotation":0,"texture":"#2","tintindex":0},"west":{"uv":[6.75,6.25,7.0,7.0],"rotation":270,"texture":"#2","tintindex":0}}},{"name":"3_47","from":[13.9428005,7.483971,5.989479],"to":[14.417297,7.9584694,6.463977],"rotation":{"angle":0.0,"axis":"x","origin":[8.115861,7.7212195,7.534046]},"faces":{"down":{"uv":[7.75,6.5,8.0,6.25],"rotation":0,"texture":"#2","tintindex":0},"east":{"uv":[7.75,6.25,8.0,6.5],"rotation":90,"texture":"#2","tintindex":0},"north":{"uv":[8.0,6.25,7.75,6.5],"rotation":0,"texture":"#2","tintindex":0},"south":{"uv":[7.75,6.25,8.0,6.5],"rotation":0,"texture":"#2","tintindex":0},"up":{"uv":[7.75,6.25,8.0,6.5],"rotation":0,"texture":"#2","tintindex":0},"west":{"uv":[7.75,6.25,8.0,6.5],"rotation":270,"texture":"#2","tintindex":0}}},{"name":"3_48","from":[17.738785,7.483971,5.989479],"to":[18.213284,7.9584694,6.463977],"rotation":{"angle":0.0,"axis":"x","origin":[8.115861,7.7212195,7.534046]},"faces":{"down":{"uv":[9.75,6.5,10.0,6.25],"rotation":0,"texture":"#2","tintindex":0},"east":{"uv":[9.75,6.25,10.0,6.5],"rotation":90,"texture":"#2","tintindex":0},"north":{"uv":[10.0,6.25,9.75,6.5],"rotation":0,"texture":"#2","tintindex":0},"south":{"uv":[9.75,6.25,10.0,6.5],"rotation":0,"texture":"#2","tintindex":0},"up":{"uv":[9.75,6.25,10.0,6.5],"rotation":0,"texture":"#2","tintindex":0},"west":{"uv":[9.75,6.25,10.0,6.5],"rotation":270,"texture":"#2","tintindex":0}}},{"name":"3_49","from":[8.723322,7.483971,6.463977],"to":[9.19782,7.9584694,7.887471],"rotation":{"angle":0.0,"axis":"x","origin":[8.115861,7.7212195,7.534046]},"faces":{"down":{"uv":[5.0,7.25,5.25,6.5],"rotation":0,"texture":"#2","tintindex":0},"east":{"uv":[5.0,6.5,5.25,7.25],"rotation":90,"texture":"#2","tintindex":0},"north":{"uv":[5.25,6.5,5.0,6.75],"rotation":0,"texture":"#2","tintindex":0},"south":{"uv":[5.0,7.0,5.25,7.25],"rotation":0,"texture":"#2","tintindex":0},"up":{"uv":[5.0,6.5,5.25,7.25],"rotation":0,"texture":"#2","tintindex":0},"west":{"uv":[5.0,6.5,5.25,7.25],"rotation":270,"texture":"#2","tintindex":0}}},{"name":"3_50","from":[11.095812,7.483971,6.463977],"to":[12.044808,7.9584694,7.4129734],"rotation":{"angle":0.0,"axis":"x","origin":[8.115861,7.7212195,7.534046]},"faces":{"down":{"uv":[6.25,7.0,6.75,6.5],"rotation":0,"texture":"#2","tintindex":0},"east":{"uv":[6.5,6.5,6.75,7.0],"rotation":90,"texture":"#2","tintindex":0},"north":{"uv":[6.75,6.5,6.25,6.75],"rotation":0,"texture":"#2","tintindex":0},"south":{"uv":[6.25,6.75,6.75,7.0],"rotation":0,"texture":"#2","tintindex":0},"up":{"uv":[6.25,6.5,6.75,7.0],"rotation":0,"texture":"#2","tintindex":0},"west":{"uv":[6.25,6.5,6.5,7.0],"rotation":270,"texture":"#2","tintindex":0}}},{"name":"3_51","from":[10.146816,7.483971,6.9384747],"to":[11.095812,7.9584694,7.887471],"rotation":{"angle":0.0,"axis":"x","origin":[8.115861,7.7212195,7.534046]},"faces":{"down":{"uv":[5.75,7.25,6.25,6.75],"rotation":0,"texture":"#2","tintindex":0},"east":{"uv":[6.0,6.75,6.25,7.25],"rotation":90,"texture":"#2","tintindex":0},"north":{"uv":[6.25,6.75,5.75,7.0],"rotation":0,"texture":"#2","tintindex":0},"south":{"uv":[5.75,7.0,6.25,7.25],"rotation":0,"texture":"#2","tintindex":0},"up":{"uv":[5.75,6.75,6.25,7.25],"rotation":0,"texture":"#2","tintindex":0},"west":{"uv":[5.75,6.75,6.0,7.25],"rotation":270,"texture":"#2","tintindex":0}}},{"name":"3_53","from":[7.774326,7.483971,7.4129734],"to":[8.723322,7.9584694,8.361969],"rotation":{"angle":0.0,"axis":"x","origin":[8.115861,7.7212195,7.534046]},"faces":{"down":{"uv":[4.5,7.5,5.0,7.0],"rotation":0,"texture":"#2","tintindex":0},"east":{"uv":[4.75,7.0,5.0,7.5],"rotation":90,"texture":"#2","tintindex":0},"north":{"uv":[5.0,7.0,4.5,7.25],"rotation":0,"texture":"#2","tintindex":0},"south":{"uv":[4.5,7.25,5.0,7.5],"rotation":0,"texture":"#2","tintindex":0},"up":{"uv":[4.5,7.0,5.0,7.5],"rotation":0,"texture":"#2","tintindex":0},"west":{"uv":[4.5,7.0,4.75,7.5],"rotation":270,"texture":"#2","tintindex":0}}},{"name":"3_54","from":[9.6723175,7.483971,7.4129734],"to":[10.146816,7.9584694,7.887471],"rotation":{"angle":0.0,"axis":"x","origin":[8.115861,7.7212195,7.534046]},"faces":{"down":{"uv":[5.5,7.25,5.75,7.0],"rotation":0,"texture":"#2","tintindex":0},"east":{"uv":[5.5,7.0,5.75,7.25],"rotation":90,"texture":"#2","tintindex":0},"north":{"uv":[5.75,7.0,5.5,7.25],"rotation":0,"texture":"#2","tintindex":0},"south":{"uv":[5.5,7.0,5.75,7.25],"rotation":0,"texture":"#2","tintindex":0},"up":{"uv":[5.5,7.0,5.75,7.25],"rotation":0,"texture":"#2","tintindex":0},"west":{"uv":[5.5,7.0,5.75,7.25],"rotation":270,"texture":"#2","tintindex":0}}},{"name":"3_55","from":[7.2998276,7.483971,7.887471],"to":[7.774326,7.9584694,9.310966],"rotation":{"angle":0.0,"axis":"x","origin":[8.115861,7.7212195,7.534046]},"faces":{"down":{"uv":[4.25,8.0,4.5,7.25],"rotation":0,"texture":"#2","tintindex":0},"east":{"uv":[4.25,7.25,4.5,8.0],"rotation":90,"texture":"#2","tintindex":0},"north":{"uv":[4.5,7.25,4.25,7.5],"rotation":0,"texture":"#2","tintindex":0},"south":{"uv":[4.25,7.75,4.5,8.0],"rotation":0,"texture":"#2","tintindex":0},"up":{"uv":[4.25,7.25,4.5,8.0],"rotation":0,"texture":"#2","tintindex":0},"west":{"uv":[4.25,7.25,4.5,8.0],"rotation":270,"texture":"#2","tintindex":0}}},{"name":"3_56","from":[6.82533,7.483971,8.361969],"to":[7.2998276,7.9584694,9.785463],"rotation":{"angle":0.0,"axis":"x","origin":[8.115861,7.7212195,7.534046]},"faces":{"down":{"uv":[4.0,8.25,4.25,7.5],"rotation":0,"texture":"#2","tintindex":0},"east":{"uv":[4.0,7.5,4.25,8.25],"rotation":90,"texture":"#2","tintindex":0},"north":{"uv":[4.25,7.5,4.0,7.75],"rotation":0,"texture":"#2","tintindex":0},"south":{"uv":[4.0,8.0,4.25,8.25],"rotation":0,"texture":"#2","tintindex":0},"up":{"uv":[4.0,7.5,4.25,8.25],"rotation":0,"texture":"#2","tintindex":0},"west":{"uv":[4.0,7.5,4.25,8.25],"rotation":270,"texture":"#2","tintindex":0}}},{"name":"3_57","from":[7.774326,7.483971,8.361969],"to":[8.248823,7.9584694,8.836467],"rotation":{"angle":0.0,"axis":"x","origin":[8.115861,7.7212195,7.534046]},"faces":{"down":{"uv":[4.5,7.75,4.75,7.5],"rotation":0,"texture":"#2","tintindex":0},"east":{"uv":[4.5,7.5,4.75,7.75],"rotation":90,"texture":"#2","tintindex":0},"north":{"uv":[4.75,7.5,4.5,7.75],"rotation":0,"texture":"#2","tintindex":0},"south":{"uv":[4.5,7.5,4.75,7.75],"rotation":0,"texture":"#2","tintindex":0},"up":{"uv":[4.5,7.5,4.75,7.75],"rotation":0,"texture":"#2","tintindex":0},"west":{"uv":[4.5,7.5,4.75,7.75],"rotation":270,"texture":"#2","tintindex":0}}},{"name":"3_58","from":[6.350831,7.483971,8.836467],"to":[6.82533,7.9584694,10.259961],"rotation":{"angle":0.0,"axis":"x","origin":[8.115861,7.7212195,7.534046]},"faces":{"down":{"uv":[3.75,8.5,4.0,7.75],"rotation":0,"texture":"#2","tintindex":0},"east":{"uv":[3.75,7.75,4.0,8.5],"rotation":90,"texture":"#2","tintindex":0},"north":{"uv":[4.0,7.75,3.75,8.0],"rotation":0,"texture":"#2","tintindex":0},"south":{"uv":[3.75,8.25,4.0,8.5],"rotation":0,"texture":"#2","tintindex":0},"up":{"uv":[3.75,7.75,4.0,8.5],"rotation":0,"texture":"#2","tintindex":0},"west":{"uv":[3.75,7.75,4.0,8.5],"rotation":270,"texture":"#2","tintindex":0}}},{"name":"3_59","from":[5.876333,7.483971,9.310966],"to":[6.350831,7.9584694,10.734459],"rotation":{"angle":0.0,"axis":"x","origin":[8.115861,7.7212195,7.534046]},"faces":{"down":{"uv":[3.5,8.75,3.75,8.0],"rotation":0,"texture":"#2","tintindex":0},"east":{"uv":[3.5,8.0,3.75,8.75],"rotation":90,"texture":"#2","tintindex":0},"north":{"uv":[3.75,8.0,3.5,8.25],"rotation":0,"texture":"#2","tintindex":0},"south":{"uv":[3.5,8.5,3.75,8.75],"rotation":0,"texture":"#2","tintindex":0},"up":{"uv":[3.5,8.0,3.75,8.75],"rotation":0,"texture":"#2","tintindex":0},"west":{"uv":[3.5,8.0,3.75,8.75],"rotation":270,"texture":"#2","tintindex":0}}},{"name":"3_60","from":[5.4018354,7.483971,9.785463],"to":[5.876333,7.9584694,11.208958],"rotation":{"angle":0.0,"axis":"x","origin":[8.115861,7.7212195,7.534046]},"faces":{"down":{"uv":[3.25,9.0,3.5,8.25],"rotation":0,"texture":"#2","tintindex":0},"east":{"uv":[3.25,8.25,3.5,9.0],"rotation":90,"texture":"#2","tintindex":0},"north":{"uv":[3.5,8.25,3.25,8.5],"rotation":0,"texture":"#2","tintindex":0},"south":{"uv":[3.25,8.75,3.5,9.0],"rotation":0,"texture":"#2","tintindex":0},"up":{"uv":[3.25,8.25,3.5,9.0],"rotation":0,"texture":"#2","tintindex":0},"west":{"uv":[3.25,8.25,3.5,9.0],"rotation":270,"texture":"#2","tintindex":0}}},{"name":"3_61","from":[4.927337,7.483971,10.259961],"to":[5.4018354,7.9584694,11.683455],"rotation":{"angle":0.0,"axis":"x","origin":[8.115861,7.7212195,7.534046]},"faces":{"down":{"uv":[3.0,9.25,3.25,8.5],"rotation":0,"texture":"#2","tintindex":0},"east":{"uv":[3.0,8.5,3.25,9.25],"rotation":90,"texture":"#2","tintindex":0},"north":{"uv":[3.25,8.5,3.0,8.75],"rotation":0,"texture":"#2","tintindex":0},"south":{"uv":[3.0,9.0,3.25,9.25],"rotation":0,"texture":"#2","tintindex":0},"up":{"uv":[3.0,8.5,3.25,9.25],"rotation":0,"texture":"#2","tintindex":0},"west":{"uv":[3.0,8.5,3.25,9.25],"rotation":270,"texture":"#2","tintindex":0}}},{"name":"3_62","from":[4.4528394,7.483971,10.734459],"to":[4.927337,7.9584694,12.157953],"rotation":{"angle":0.0,"axis":"x","origin":[8.115861,7.7212195,7.534046]},"faces":{"down":{"uv":[2.75,9.5,3.0,8.75],"rotation":0,"texture":"#2","tintindex":0},"east":{"uv":[2.75,8.75,3.0,9.5],"rotation":90,"texture":"#2","tintindex":0},"north":{"uv":[3.0,8.75,2.75,9.0],"rotation":0,"texture":"#2","tintindex":0},"south":{"uv":[2.75,9.25,3.0,9.5],"rotation":0,"texture":"#2","tintindex":0},"up":{"uv":[2.75,8.75,3.0,9.5],"rotation":0,"texture":"#2","tintindex":0},"west":{"uv":[2.75,8.75,3.0,9.5],"rotation":270,"texture":"#2","tintindex":0}}},{"name":"3_63","from":[3.9783416,7.483971,11.208958],"to":[4.4528394,7.9584694,12.632451],"rotation":{"angle":0.0,"axis":"x","origin":[8.115861,7.7212195,7.534046]},"faces":{"down":{"uv":[2.5,9.75,2.75,9.0],"rotation":0,"texture":"#2","tintindex":0},"east":{"uv":[2.5,9.0,2.75,9.75],"rotation":90,"texture":"#2","tintindex":0},"north":{"uv":[2.75,9.0,2.5,9.25],"rotation":0,"texture":"#2","tintindex":0},"south":{"uv":[2.5,9.5,2.75,9.75],"rotation":0,"texture":"#2","tintindex":0},"up":{"uv":[2.5,9.0,2.75,9.75],"rotation":0,"texture":"#2","tintindex":0},"west":{"uv":[2.5,9.0,2.75,9.75],"rotation":270,"texture":"#2","tintindex":0}}},{"name":"3_64","from":[3.5038433,7.483971,11.683455],"to":[3.9783416,7.9584694,13.106949],"rotation":{"angle":0.0,"axis":"x","origin":[8.115861,7.7212195,7.534046]},"faces":{"down":{"uv":[2.25,10.0,2.5,9.25],"rotation":0,"texture":"#2","tintindex":0},"east":{"uv":[2.25,9.25,2.5,10.0],"rotation":90,"texture":"#2","tintindex":0},"north":{"uv":[2.5,9.25,2.25,9.5],"rotation":0,"texture":"#2","tintindex":0},"south":{"uv":[2.25,9.75,2.5,10.0],"rotation":0,"texture":"#2","tintindex":0},"up":{"uv":[2.25,9.25,2.5,10.0],"rotation":0,"texture":"#2","tintindex":0},"west":{"uv":[2.25,9.25,2.5,10.0],"rotation":270,"texture":"#2","tintindex":0}}},{"name":"3_65","from":[3.0293455,7.483971,12.157953],"to":[3.5038433,7.9584694,13.581448],"rotation":{"angle":0.0,"axis":"x","origin":[8.115861,7.7212195,7.534046]},"faces":{"down":{"uv":[2.0,10.25,2.25,9.5],"rotation":0,"texture":"#2","tintindex":0},"east":{"uv":[2.0,9.5,2.25,10.25],"rotation":90,"texture":"#2","tintindex":0},"north":{"uv":[2.25,9.5,2.0,9.75],"rotation":0,"texture":"#2","tintindex":0},"south":{"uv":[2.0,10.0,2.25,10.25],"rotation":0,"texture":"#2","tintindex":0},"up":{"uv":[2.0,9.5,2.25,10.25],"rotation":0,"texture":"#2","tintindex":0},"west":{"uv":[2.0,9.5,2.25,10.25],"rotation":270,"texture":"#2","tintindex":0}}},{"name":"3_66","from":[2.5548472,7.483971,12.632451],"to":[3.0293455,7.9584694,14.055945],"rotation":{"angle":0.0,"axis":"x","origin":[8.115861,7.7212195,7.534046]},"faces":{"down":{"uv":[1.75,10.5,2.0,9.75],"rotation":0,"texture":"#2","tintindex":0},"east":{"uv":[1.75,9.75,2.0,10.5],"rotation":90,"texture":"#2","tintindex":0},"north":{"uv":[2.0,9.75,1.75,10.0],"rotation":0,"texture":"#2","tintindex":0},"south":{"uv":[1.75,10.25,2.0,10.5],"rotation":0,"texture":"#2","tintindex":0},"up":{"uv":[1.75,9.75,2.0,10.5],"rotation":0,"texture":"#2","tintindex":0},"west":{"uv":[1.75,9.75,2.0,10.5],"rotation":270,"texture":"#2","tintindex":0}}},{"name":"3_67","from":[2.08035,7.483971,13.106949],"to":[2.5548472,7.9584694,14.530443],"rotation":{"angle":0.0,"axis":"x","origin":[8.115861,7.7212195,7.534046]},"faces":{"down":{"uv":[1.5,10.75,1.75,10.0],"rotation":0,"texture":"#2","tintindex":0},"east":{"uv":[1.5,10.0,1.75,10.75],"rotation":90,"texture":"#2","tintindex":0},"north":{"uv":[1.75,10.0,1.5,10.25],"rotation":0,"texture":"#2","tintindex":0},"south":{"uv":[1.5,10.5,1.75,10.75],"rotation":0,"texture":"#2","tintindex":0},"up":{"uv":[1.5,10.0,1.75,10.75],"rotation":0,"texture":"#2","tintindex":0},"west":{"uv":[1.5,10.0,1.75,10.75],"rotation":270,"texture":"#2","tintindex":0}}},{"name":"3_68","from":[1.6058515,7.483971,13.581448],"to":[2.08035,7.9584694,15.004941],"rotation":{"angle":0.0,"axis":"x","origin":[8.115861,7.7212195,7.534046]},"faces":{"down":{"uv":[1.25,11.0,1.5,10.25],"rotation":0,"texture":"#2","tintindex":0},"east":{"uv":[1.25,10.25,1.5,11.0],"rotation":90,"texture":"#2","tintindex":0},"north":{"uv":[1.5,10.25,1.25,10.5],"rotation":0,"texture":"#2","tintindex":0},"south":{"uv":[1.25,10.75,1.5,11.0],"rotation":0,"texture":"#2","tintindex":0},"up":{"uv":[1.25,10.25,1.5,11.0],"rotation":0,"texture":"#2","tintindex":0},"west":{"uv":[1.25,10.25,1.5,11.0],"rotation":270,"texture":"#2","tintindex":0}}},{"name":"3_69","from":[1.1313531,7.483971,14.055945],"to":[1.6058515,7.9584694,15.47944],"rotation":{"angle":0.0,"axis":"x","origin":[8.115861,7.7212195,7.534046]},"faces":{"down":{"uv":[1.0,11.25,1.25,10.5],"rotation":0,"texture":"#2","tintindex":0},"east":{"uv":[1.0,10.5,1.25,11.25],"rotation":90,"texture":"#2","tintindex":0},"north":{"uv":[1.25,10.5,1.0,10.75],"rotation":0,"texture":"#2","tintindex":0},"south":{"uv":[1.0,11.0,1.25,11.25],"rotation":0,"texture":"#2","tintindex":0},"up":{"uv":[1.0,10.5,1.25,11.25],"rotation":0,"texture":"#2","tintindex":0},"west":{"uv":[1.0,10.5,1.25,11.25],"rotation":270,"texture":"#2","tintindex":0}}},{"name":"3_70","from":[0.6568558,7.483971,14.530443],"to":[1.1313531,7.9584694,15.953938],"rotation":{"angle":0.0,"axis":"x","origin":[8.115861,7.7212195,7.534046]},"faces":{"down":{"uv":[0.75,11.5,1.0,10.75],"rotation":0,"texture":"#2","tintindex":0},"east":{"uv":[0.75,10.75,1.0,11.5],"rotation":90,"texture":"#2","tintindex":0},"north":{"uv":[1.0,10.75,0.75,11.0],"rotation":0,"texture":"#2","tintindex":0},"south":{"uv":[0.75,11.25,1.0,11.5],"rotation":0,"texture":"#2","tintindex":0},"up":{"uv":[0.75,10.75,1.0,11.5],"rotation":0,"texture":"#2","tintindex":0},"west":{"uv":[0.75,10.75,1.0,11.5],"rotation":270,"texture":"#2","tintindex":0}}},{"name":"3_71","from":[0.18235755,7.483971,15.004941],"to":[0.6568558,7.9584694,16.902935],"rotation":{"angle":0.0,"axis":"x","origin":[8.115861,7.7212195,7.534046]},"faces":{"down":{"uv":[0.5,12.0,0.75,11.0],"rotation":0,"texture":"#2","tintindex":0},"east":{"uv":[0.5,11.0,0.75,12.0],"rotation":90,"texture":"#2","tintindex":0},"north":{"uv":[0.75,11.0,0.5,11.25],"rotation":0,"texture":"#2","tintindex":0},"south":{"uv":[0.5,11.75,0.75,12.0],"rotation":0,"texture":"#2","tintindex":0},"up":{"uv":[0.5,11.0,0.75,12.0],"rotation":0,"texture":"#2","tintindex":0},"west":{"uv":[0.5,11.0,0.75,12.0],"rotation":270,"texture":"#2","tintindex":0}}},{"name":"3_72","from":[-0.76663804,7.483971,15.47944],"to":[0.18235755,7.9584694,16.902935],"rotation":{"angle":0.0,"axis":"x","origin":[8.115861,7.7212195,7.534046]},"faces":{"down":{"uv":[0.0,12.0,0.5,11.25],"rotation":0,"texture":"#2","tintindex":0},"east":{"uv":[0.25,11.25,0.5,12.0],"rotation":90,"texture":"#2","tintindex":0},"north":{"uv":[0.5,11.25,0.0,11.5],"rotation":0,"texture":"#2","tintindex":0},"south":{"uv":[0.0,11.75,0.5,12.0],"rotation":0,"texture":"#2","tintindex":0},"up":{"uv":[0.0,11.25,0.5,12.0],"rotation":0,"texture":"#2","tintindex":0},"west":{"uv":[0.0,11.25,0.25,12.0],"rotation":270,"texture":"#2","tintindex":0}}}],"display":{"head":{"translation":[0.0,-6.4,0.0],"rotation":[0.0,0.0,0.0],"scale":[3.8095,3.8095,3.8095]}}}