{"textures":{"0":"modelengine:entity/rp"},"elements":[{"name":"cube","from":[7.19,5.21,8.0],"to":[8.81,8.4800005,8.0],"rotation":{"angle":0.0,"axis":"x","origin":[8.0,6.8450003,8.0]},"faces":{"down":{"uv":[0.34375,0.0,0.0,0.0],"rotation":0,"texture":"#0","tintindex":0},"east":{"uv":[0.0,0.0,0.0,0.6875],"rotation":0,"texture":"#0","tintindex":0},"north":{"uv":[3.375,11.875,3.71875,12.5625],"rotation":0,"texture":"#0","tintindex":0},"south":{"uv":[4.75,12.125,5.09375,12.8125],"rotation":0,"texture":"#0","tintindex":0},"up":{"uv":[0.34375,0.0,0.0,0.0],"rotation":0,"texture":"#0","tintindex":0},"west":{"uv":[0.0,0.0,0.0,0.6875],"rotation":0,"texture":"#0","tintindex":0}}},{"name":"cube","from":[7.19,5.21,8.0],"to":[8.81,8.4800005,8.0],"rotation":{"angle":0.0,"axis":"x","origin":[8.0,6.8450003,8.0]},"faces":{"down":{"uv":[0.34375,0.0,0.0,0.0],"rotation":0,"texture":"#0","tintindex":0},"east":{"uv":[0.0,0.0,0.0,0.6875],"rotation":0,"texture":"#0","tintindex":0},"north":{"uv":[5.125,12.125,5.46875,12.8125],"rotation":0,"texture":"#0","tintindex":0},"south":{"uv":[5.5,12.125,5.84375,12.8125],"rotation":0,"texture":"#0","tintindex":0},"up":{"uv":[0.34375,0.0,0.0,0.0],"rotation":0,"texture":"#0","tintindex":0},"west":{"uv":[0.0,0.0,0.0,0.6875],"rotation":0,"texture":"#0","tintindex":0}}}],"display":{"head":{"translation":[0.0,-6.4,0.0],"rotation":[0.0,0.0,0.0],"scale":[3.8095,3.8095,3.8095]}}}