{"textures":{"0":"modelengine:entity/rp"},"elements":[{"name":"cube","from":[7.3849998,6.2599993,7.31],"to":[8.014999,8.059999,8.69],"rotation":{"angle":0.0,"axis":"x","origin":[7.7,7.159999,8.0]},"faces":{"down":{"uv":[13.5,8.75,13.375,9.03125],"rotation":0,"texture":"#0","tintindex":0},"east":{"uv":[12.75,11.25,13.03125,11.625],"rotation":0,"texture":"#0","tintindex":0},"north":{"uv":[4.75,11.25,4.875,11.625],"rotation":0,"texture":"#0","tintindex":0},"south":{"uv":[9.375,11.25,9.5,11.625],"rotation":0,"texture":"#0","tintindex":0},"up":{"uv":[10.25,13.53125,10.125,13.25],"rotation":0,"texture":"#0","tintindex":0},"west":{"uv":[12.75,12.0,13.03125,12.375],"rotation":0,"texture":"#0","tintindex":0}}}],"display":{"head":{"translation":[0.0,-6.4,0.0],"rotation":[0.0,0.0,0.0],"scale":[3.8095,3.8095,3.8095]}}}