{"textures":{"0":"modelengine:entity/rp"},"elements":[{"name":"cube","from":[8.42,7.5800753,6.9649997],"to":[8.42,8.420076,9.035],"rotation":{"angle":0.0,"axis":"x","origin":[8.42,8.000075,8.0]},"faces":{"down":{"uv":[0.0,0.0,0.0,0.4375],"rotation":0,"texture":"#0","tintindex":0},"east":{"uv":[12.875,7.375,13.3125,7.546875],"rotation":0,"texture":"#0","tintindex":0},"north":{"uv":[0.0,0.0,0.0,0.171875],"rotation":0,"texture":"#0","tintindex":0},"south":{"uv":[0.0,0.0,0.0,0.171875],"rotation":0,"texture":"#0","tintindex":0},"up":{"uv":[0.0,0.4375,0.0,0.0],"rotation":0,"texture":"#0","tintindex":0},"west":{"uv":[13.125,2.25,13.5625,2.421875],"rotation":0,"texture":"#0","tintindex":0}}},{"name":"cube","from":[8.42,7.5800753,6.9649997],"to":[8.42,8.420076,9.035],"rotation":{"angle":0.0,"axis":"x","origin":[8.42,8.000075,8.0]},"faces":{"down":{"uv":[0.0,0.0,0.0,0.4375],"rotation":0,"texture":"#0","tintindex":0},"east":{"uv":[13.125,3.25,13.5625,3.421875],"rotation":0,"texture":"#0","tintindex":0},"north":{"uv":[0.0,0.0,0.0,0.171875],"rotation":0,"texture":"#0","tintindex":0},"south":{"uv":[0.0,0.0,0.0,0.171875],"rotation":0,"texture":"#0","tintindex":0},"up":{"uv":[0.0,0.4375,0.0,0.0],"rotation":0,"texture":"#0","tintindex":0},"west":{"uv":[13.125,3.5,13.5625,3.671875],"rotation":0,"texture":"#0","tintindex":0}}},{"name":"cube","from":[7.58,7.5800753,6.9649997],"to":[7.58,8.420076,9.035],"rotation":{"angle":0.0,"axis":"x","origin":[7.58,8.000075,8.0]},"faces":{"down":{"uv":[0.0,0.0,0.0,0.4375],"rotation":0,"texture":"#0","tintindex":0},"east":{"uv":[13.125,3.75,13.5625,3.921875],"rotation":0,"texture":"#0","tintindex":0},"north":{"uv":[0.0,0.0,0.0,0.171875],"rotation":0,"texture":"#0","tintindex":0},"south":{"uv":[0.0,0.0,0.0,0.171875],"rotation":0,"texture":"#0","tintindex":0},"up":{"uv":[0.0,0.4375,0.0,0.0],"rotation":0,"texture":"#0","tintindex":0},"west":{"uv":[13.125,4.0,13.5625,4.171875],"rotation":0,"texture":"#0","tintindex":0}}},{"name":"cube","from":[7.58,7.5800753,6.9649997],"to":[7.58,8.420076,9.035],"rotation":{"angle":0.0,"axis":"x","origin":[7.58,8.000075,8.0]},"faces":{"down":{"uv":[0.0,0.0,0.0,0.4375],"rotation":0,"texture":"#0","tintindex":0},"east":{"uv":[13.125,4.25,13.5625,4.421875],"rotation":0,"texture":"#0","tintindex":0},"north":{"uv":[0.0,0.0,0.0,0.171875],"rotation":0,"texture":"#0","tintindex":0},"south":{"uv":[0.0,0.0,0.0,0.171875],"rotation":0,"texture":"#0","tintindex":0},"up":{"uv":[0.0,0.4375,0.0,0.0],"rotation":0,"texture":"#0","tintindex":0},"west":{"uv":[13.125,4.5,13.5625,4.671875],"rotation":0,"texture":"#0","tintindex":0}}},{"name":"cube","from":[7.58,8.420076,6.9649997],"to":[8.42,8.420076,9.035],"rotation":{"angle":0.0,"axis":"x","origin":[8.0,8.420076,8.0]},"faces":{"down":{"uv":[8.546875,13.0,8.375,13.4375],"rotation":0,"texture":"#0","tintindex":0},"east":{"uv":[0.0,0.0,0.4375,0.0],"rotation":0,"texture":"#0","tintindex":0},"north":{"uv":[0.0,0.0,0.171875,0.0],"rotation":0,"texture":"#0","tintindex":0},"south":{"uv":[0.0,0.0,0.171875,0.0],"rotation":0,"texture":"#0","tintindex":0},"up":{"uv":[10.421875,13.3125,10.25,12.875],"rotation":0,"texture":"#0","tintindex":0},"west":{"uv":[0.0,0.0,0.4375,0.0],"rotation":0,"texture":"#0","tintindex":0}}},{"name":"cube","from":[7.58,8.420074,6.9649997],"to":[8.42,8.420074,9.035],"rotation":{"angle":0.0,"axis":"x","origin":[8.0,8.420074,8.0]},"faces":{"down":{"uv":[13.296875,4.75,13.125,5.1875],"rotation":0,"texture":"#0","tintindex":0},"east":{"uv":[0.0,0.0,0.4375,0.0],"rotation":0,"texture":"#0","tintindex":0},"north":{"uv":[0.0,0.0,0.171875,0.0],"rotation":0,"texture":"#0","tintindex":0},"south":{"uv":[0.0,0.0,0.171875,0.0],"rotation":0,"texture":"#0","tintindex":0},"up":{"uv":[11.671875,13.4375,11.5,13.0],"rotation":0,"texture":"#0","tintindex":0},"west":{"uv":[0.0,0.0,0.4375,0.0],"rotation":0,"texture":"#0","tintindex":0}}},{"name":"cube","from":[7.58,7.5800753,6.9649997],"to":[8.42,7.5800753,9.035],"rotation":{"angle":0.0,"axis":"x","origin":[8.0,7.5800753,8.0]},"faces":{"down":{"uv":[5.921875,13.125,5.75,13.5625],"rotation":0,"texture":"#0","tintindex":0},"east":{"uv":[0.0,0.0,0.4375,0.0],"rotation":0,"texture":"#0","tintindex":0},"north":{"uv":[0.0,0.0,0.171875,0.0],"rotation":0,"texture":"#0","tintindex":0},"south":{"uv":[0.0,0.0,0.171875,0.0],"rotation":0,"texture":"#0","tintindex":0},"up":{"uv":[13.296875,5.6875,13.125,5.25],"rotation":0,"texture":"#0","tintindex":0},"west":{"uv":[0.0,0.0,0.4375,0.0],"rotation":0,"texture":"#0","tintindex":0}}},{"name":"cube","from":[7.58,7.5794754,6.9649997],"to":[8.42,7.5794754,9.035],"rotation":{"angle":0.0,"axis":"x","origin":[8.0,7.5794754,8.0]},"faces":{"down":{"uv":[6.171875,13.125,6.0,13.5625],"rotation":0,"texture":"#0","tintindex":0},"east":{"uv":[0.0,0.0,0.4375,0.0],"rotation":0,"texture":"#0","tintindex":0},"north":{"uv":[0.0,0.0,0.171875,0.0],"rotation":0,"texture":"#0","tintindex":0},"south":{"uv":[0.0,0.0,0.171875,0.0],"rotation":0,"texture":"#0","tintindex":0},"up":{"uv":[13.296875,6.1875,13.125,5.75],"rotation":0,"texture":"#0","tintindex":0},"west":{"uv":[0.0,0.0,0.4375,0.0],"rotation":0,"texture":"#0","tintindex":0}}}],"display":{"head":{"translation":[0.0,-6.4,0.0],"rotation":[0.0,0.0,0.0],"scale":[3.8095,3.8095,3.8095]}}}